bababel/__init__.py
bababel/bababel_app.py
bababel/consumer/__init__.py
bababel/consumer/consumer.py
bababel/dataclasses/__init__.py
bababel/dataclasses/queue_callback_bind.py
bababel/exceptions/__init__.py
bababel/exceptions/base_bababel_error.py
bababel/publisher/__init__.py
bababel/publisher/publisher.py
bababel/rabbitmq/__init__.py
bababel/rabbitmq/rabbitmq_client.py
bababel/rabbitmq/rabbitmq_connection.py
bababel/task/__init__.py
bababel/task/task.py
bababel/utils/__init__.py
bababel/utils/utils.py
bababel-0.4.1.dist-info/LICENSE
bababel-0.4.1.dist-info/METADATA
bababel-0.4.1.dist-info/WHEEL
bababel-0.4.1.dist-info/top_level.txt
bababel-0.4.1.dist-info/RECORD
