Metadata-Version: 2.2
Name: bababel
Version: 0.4.1
Summary: A messaging consumer library for handling and processing messages efficiently.
Author-email: Gustavo Delai Onzi Da Silva <gustavodelai11@gmail.com>
License: MIT
Project-URL: Homepage, https://github.com/GustavoDelaiOnzi/bababel
License-File: LICENSE
Requires-Dist: pika<2.0,>=1.3.2
Requires-Dist: nanoid<3.0,>=2.0.0
Provides-Extra: dev
Requires-Dist: pytest<9.0,>=8.3.4; extra == "dev"
Requires-Dist: flake8<8.0,>=7.1.1; extra == "dev"
Requires-Dist: black<26.0,>=25.1.0; extra == "dev"
Requires-Dist: isort<7.0,>=6.0.0; extra == "dev"
Requires-Dist: commitizen<5.0,>=4.2.1; extra == "dev"
Requires-Dist: pre-commit<5.0,>=4.1.0; extra == "dev"
Requires-Dist: pytest<9.0,>=8.3.4; extra == "dev"
Requires-Dist: pytest-mock<4.0,>=3.14.0; extra == "dev"
Requires-Dist: pytest-cov<7.0,>=6.0.0; extra == "dev"
Requires-Dist: twine<7.0,>=6.1.0; extra == "dev"
Requires-Dist: build<2.0,>=1.2.2; extra == "dev"
